README.rst
setup.py
gerber/__init__.py
gerber/__main__.py
gerber/am_eval.py
gerber/am_read.py
gerber/am_statements.py
gerber/cam.py
gerber/common.py
gerber/excellon.py
gerber/excellon_settings.py
gerber/excellon_statements.py
gerber/excellon_tool.py
gerber/exceptions.py
gerber/gerber_statements.py
gerber/ipc356.py
gerber/layers.py
gerber/operations.py
gerber/pcb.py
gerber/primitives.py
gerber/rs274x.py
gerber/utils.py
gerber/render/__init__.py
gerber/render/cairo_backend.py
gerber/render/excellon_backend.py
gerber/render/render.py
gerber/render/rs274x_backend.py
gerber/render/theme.py
pcb_tools.egg-info/PKG-INFO
pcb_tools.egg-info/SOURCES.txt
pcb_tools.egg-info/dependency_links.txt
pcb_tools.egg-info/requires.txt
pcb_tools.egg-info/top_level.txt