Metadata-Version: 2.1
Name: pcb-tools
Version: 0.1.3
Summary: Utilities to handle Gerber (RS-274X) files.
Home-page: http://github.com/curtacircuitos/pcb-tools
Author: Paulo Henrique Silva <ph.silva@gmail.com>, Hamilton Kibbe <ham@hamiltonkib.be>
Author-email: ph.silva@gmail.com, ham@hamiltonkib.be
License: Apache
Keywords: pcb gerber tools
Platform: UNKNOWN
Classifier: Development Status :: 3 - Alpha
Classifier: Topic :: Utilities
Classifier: License :: OSI Approved :: Apple Public Source License
